facebook/__init__.py
facebook/version.py
facebook_py-0.2.dist-info/DESCRIPTION.rst
facebook_py-0.2.dist-info/METADATA
facebook_py-0.2.dist-info/RECORD
facebook_py-0.2.dist-info/WHEEL
facebook_py-0.2.dist-info/metadata.json
facebook_py-0.2.dist-info/top_level.txt
