Metadata-Version: 1.1
Name: facebook-py
Version: 0.2
Summary: This client library is designed to support the Facebook Graph API and the official Facebook JavaScript SDK, which is the canonical way to implement Facebook authentication.
Home-page: https://github.com/ratson/facebook-py
Author: Ratson
Author-email: UNKNOWN
License: Apache
Platform: UNKNOWN
Classifier: License :: OSI Approved :: Apache Software License
Classifier: Programming Language :: Python
Classifier: Programming Language :: Python :: 2.7
Classifier: Programming Language :: Python :: 3
Classifier: Programming Language :: Python :: 3.3
Classifier: Programming Language :: Python :: 3.4
Classifier: Programming Language :: Python :: 3.5
